{"unique_id": "22_00125_sgd_train", "id": "22_00125", "turns": [{"utterance": "Could you get me a taxi?", "response": "Where do you want to go? How many passengers are there? Will this be a shared ride?"}, {"utterance": "Yes, sure, a shared ride is fine. There are 2 of us and we want to go to 5251 Martinelli Way.", "response": "Please confirm that you need a taxi for 2 passengers to go to 5251 Martinelli Way and a shared ride would be okay."}, {"utterance": "Yes, that sounds like what we need.", "response": "The taxi is on its way to your location."}, {"utterance": "Could you give me an approximate cost? And is there any way you could give me an approximate time for the ride?", "response": "The total cost is approximately $17.88 and the ride will take about 23 minutes."}, {"utterance": "Great. This has been pretty easy.", "response": "Would you like me to help with anything else?"}, {"utterance": "No, I don't think so. I appreciate your help.", "response": "Enjoy the rest of your day."}], "annotations": [{"turn": 5, "annotation": [{"error_type": "", "comment": "no correction", "user_correction": "C2", "user_reaction": ""}, {"error_type": "", "comment": "", "user_correction": "", "user_reaction": ""}, {"error_type": "", "comment": "", "user_correction": "", "user_reaction": ""}]}], "corrections": [{"phrase": ["no i dont think so.", " no, i don't think so."], "confidence": 0.93, "turn": 5}]}