{"unique_id": "33_00045_sgd_train", "id": "33_00045", "turns": [{"utterance": "Can you recommend a salon?", "response": "Which city do you want it in?"}, {"utterance": "I would like a unisex salon located in Santa Clara.", "response": "There is a nice salon in Santa Clara, it is called About Time Barber Shop."}, {"utterance": "That sounds good.", "response": "Would you like for me to book an appointment there?"}, {"utterance": "No, I don't want to book it at this time.", "response": "Is there anything else I can help you with?"}, {"utterance": "No, that is it. Thank you.", "response": "Have a good day."}], "annotations": [{"turn": 3, "annotation": [{"error_type": "", "comment": "another \"no, dont book it now\"...", "user_correction": "C2", "user_reaction": ""}, {"error_type": "", "comment": "", "user_correction": "", "user_reaction": ""}, {"error_type": "", "comment": "", "user_correction": "", "user_reaction": ""}]}], "corrections": [{"phrase": ["im not ready to book just yet.", " no, i don't want to book it at this time."], "confidence": 0.722, "turn": 3}]}