{"unique_id": "107_00068_sgd_train", "id": "107_00068", "turns": [{"utterance": "Pull up online Documentary movies please.", "response": "I found 2 you may enjoy. Knock Down The House and The Invisibles. Which would you prefer?"}, {"utterance": "The Invisibles sounds good. Let's change focus and look up songs now.", "response": "I understand, If you like Selena Gomez, I found her hit Love Will Remember off the album Stars Dance."}, {"utterance": "What genre is that? Also it sounds old, isn't that from two years ago?", "response": "This is from 2013 and is a Pop song."}, {"utterance": "No, I don't like this. Pull up Caro Emerald please.", "response": "Sure, I found 1 song titled Tangled Up off the album The Shocking Miss Emerald. This track is by Caro Emerald."}, {"utterance": "yeah that is the one I wanted to hear.", "response": "Should I start this track now?"}, {"utterance": "Sure, go ahead and cast it on my kitchen speaker please.", "response": "I would love to, but first please confirm Tangled Up on the Kitchen speaker is what you would like me to play."}, {"utterance": "No, nevermind. Let's cast in on my television.", "response": "Sure, please confirm casting Tangled Up on the TV."}, {"utterance": "You got it.", "response": "Alright, great. Please enjoy!"}, {"utterance": "Find out what year did it come out and what genre of music is this?", "response": "This is a Pop song from 2013."}, {"utterance": "Great, thanks", "response": "Your welcome, can I help with anything else?"}, {"utterance": "Nope, that was all.", "response": "Ok, have a wonderful day."}], "annotations": [{"turn": 3, "annotation": [{"error_type": "", "comment": "not a correction", "user_correction": "C2", "user_reaction": ""}, {"error_type": "", "comment": "", "user_correction": "", "user_reaction": ""}, {"error_type": "", "comment": "", "user_correction": "", "user_reaction": ""}]}], "corrections": [{"phrase": ["no", " i dont like that.", " no, i don't like this."], "confidence": 0.83, "turn": 3}]}