{"target": "ok let me look into some options for you", "user_reaction_type": "", "user_reaction": "", "error_type": "", "error_text": "", "context": "<user> hello <system> hello what can i help you with today <user> id like to book a table <system> i'm on it <user> <SILENCE> <system> any preference on a type of cuisine <user> with british cuisine <system> where should it be<user> in paris <system> how many people would be in your party<user> for two people please <system> which price range are looking for<user> i am looking for a moderate restaurant <system> ", "id": 482, "id_original": "42_44_babi_train_task1"}