{"unique_id": "PMUL4398.json_multiwoz_train", "id": "PMUL4398.json", "turns": [{"utterance": "i need a place to dine in the center thats expensive", "response": "I have several options for you; do you prefer African, Asian, or British food?"}, {"utterance": "Any sort of food would be fine, as long as it is a bit expensive. Could I get the phone number for your recommendation?", "response": "There is an Afrian place named Bedouin in the centre. How does that sound?"}, {"utterance": "Sounds good, could I get that phone number? Also, could you recommend me an expensive hotel?", "response": "Bedouin's phone is 01223367660. As far as hotels go, I recommend the University Arms Hotel in the center of town."}, {"utterance": "Yes. Can you book it for me?", "response": "Sure, when would you like that reservation?"}, {"utterance": "i want to book it for 2 people and 2 nights starting from saturday.", "response": "Your booking was successful. Your reference number is FRGZWQL2 . May I help you further?"}, {"utterance": "That is all I need to know. Thanks, good bye.", "response": "Thank you so much for Cambridge TownInfo centre. Have a great day!"}], "annotations": [{"turn": 3, "annotation": [{"error_type": null, "comment": "the user asks the system to do the reservation, no correction", "user_correction": "C2", "user_reaction": ""}, {"error_type": "", "comment": "", "user_correction": "C2", "user_reaction": ""}, {"error_type": "", "comment": "", "user_correction": "C2", "user_reaction": ""}]}], "corrections": [{"phrase": ["actually, i apologize no need to book, i was just gathering information.", " can you book it for me?"], "confidence": 0.704, "turn": 3}]}